{
    "agentInfo": {
        "agentNumber": 2,
        "agentConfigs": [],
        "defaultSettings": "default_five_agents"
    },
    "sceneInfo": {
        "items": {
            "item_total_count": 0,
            "item_counts_by_type": {},
            "items": []
        },
        "map": "default"
    },
    "orderInfo": {
        "totalOrdersNum": 12,
        "orders": [
            {
                "priority": 1,
                "wantsBeverage": true,
                "seatIdx": 3,
                "foodType": "fried_potato_carrot",
                "diningOption": "dine_in",
                "flavors": [],
                "flavorDescription": ""
            },
            {
                "priority": 1,
                "wantsBeverage": true,
                "seatIdx": 6,
                "foodType": "potato_cooked",
                "diningOption": "dine_in",
                "flavors": [
                    "sour"
                ],
                "flavorDescription": "The sharper the flavor, the better."
            },
            {
                "priority": 1,
                "wantsBeverage": true,
                "seatIdx": 0,
                "foodType": "eggplant_cooked",
                "diningOption": "dine_in",
                "flavors": [
                    "salty"
                ],
                "flavorDescription": "I enjoy the umami notes in my dishes."
            },
            {
                "priority": 1,
                "wantsBeverage": true,
                "seatIdx": 1,
                "foodType": "none",
                "diningOption": "dine_in",
                "flavors": [],
                "flavorDescription": ""
            },
            {
                "priority": 1,
                "wantsBeverage": true,
                "seatIdx": 7,
                "foodType": "eggplant_cooked",
                "diningOption": "dine_in",
                "flavors": [],
                "flavorDescription": ""
            },
            {
                "priority": 1,
                "wantsBeverage": false,
                "seatIdx": 2,
                "foodType": "carrot_cut",
                "diningOption": "dine_in",
                "flavors": [],
                "flavorDescription": ""
            },
            {
                "priority": 2,
                "wantsBeverage": true,
                "seatIdx": 6,
                "foodType": "carrot_cut",
                "diningOption": "dine_in",
                "flavors": [],
                "flavorDescription": ""
            },
            {
                "priority": 2,
                "wantsBeverage": true,
                "seatIdx": 7,
                "foodType": "potato_cooked",
                "diningOption": "dine_in",
                "flavors": [],
                "flavorDescription": ""
            },
            {
                "priority": 2,
                "wantsBeverage": true,
                "seatIdx": 2,
                "foodType": "carrot_cut",
                "diningOption": "dine_in",
                "flavors": [
                    "sweet"
                ],
                "flavorDescription": "Give me something that satisfies my sugar cravings."
            },
            {
                "priority": 2,
                "wantsBeverage": false,
                "seatIdx": 1,
                "foodType": "carrot_cooked",
                "diningOption": "dine_in",
                "flavors": [
                    "salty"
                ],
                "flavorDescription": "I enjoy the umami notes in my dishes."
            },
            {
                "priority": 2,
                "wantsBeverage": true,
                "seatIdx": 0,
                "foodType": "carrot_cooked",
                "diningOption": "dine_in",
                "flavors": [
                    "salty"
                ],
                "flavorDescription": "I have a taste for the savory side."
            },
            {
                "priority": 2,
                "wantsBeverage": true,
                "seatIdx": 3,
                "foodType": "fried_potato_carrot",
                "diningOption": "dine_in",
                "flavors": [],
                "flavorDescription": ""
            }
        ]
    },
    "traceInfo": {
        "traces": []
    },
    "timeLimit": 240,
    "taskName": "task_level8_10",
    "specialEvents": []
}